{
  "dataset": "wikipedia_september_2007",
  "model": "ilnse_A2_guard_no_quality",
  "feature_set": "A2",
  "num_features": 10,
  "cache_sizes": [
    12221,
    15277,
    30554,
    45831,
    61109,
    76386
  ],
  "hr_curve": [
    {
      "cache_size_objects": 12221,
      "hit_ratio": 0.636621375
    },
    {
      "cache_size_objects": 15277,
      "hit_ratio": 0.644120875
    },
    {
      "cache_size_objects": 30554,
      "hit_ratio": 0.6703575
    },
    {
      "cache_size_objects": 45831,
      "hit_ratio": 0.689556125
    },
    {
      "cache_size_objects": 61109,
      "hit_ratio": 0.703468
    },
    {
      "cache_size_objects": 76386,
      "hit_ratio": 0.713519
    }
  ],
  "avg_hr": 0.6762738125
}