{
  "dataset": "wikipedia_september_2007",
  "model": "ilnse_A0",
  "feature_set": "A0",
  "cache_size_objects": 30554,
  "total_requests": 9000000,
  "warmup_requests": 1000000,
  "slot_size": 100000,
  "slot_log_path": "results/wikipedia_september_2007/002_ilnse_A0_30554.jsonl",
  "hit_ratio": 0.6539435,
  "cache_hits": 5231548,
  "cache_requests": 8000000,
  "num_slots": 90,
  "warmup_slots": 10,
  "cache_slots": 80,
  "pop_top_percent": 0.2,
  "label_topk_rounding": "floor",
  "label_tie_break": "none",
  "admission_policy": "top_capacity_rate",
  "admission_rate": 0.01,
  "admission_capacity_alpha": 0.05,
  "feature_windows": {
    "short": 1,
    "mid": 7,
    "long": 30
  },
  "pollution_window_slots": 1,
  "hit_contribution": {
    "hits_from_admitted": 77853,
    "reject_requests_total": 2490243
  },
  "num_features": 6,
  "slots_processed": 90,
  "miss_requests_total": 2768452,
  "miss_candidates_total": 2612483,
  "admit_budget_total": 122240,
  "admit_requests_total": 122240,
  "reject_requests_total": 2490243,
  "admit_selected_total": 122240,
  "admit_applied_total": 120712,
  "admit_true_popular_total": 5794,
  "hits_from_admitted_total": 77853,
  "pollution_total": 120712,
  "pollution_count": 91005,
  "admission_precision_total": 0.04799854198422692,
  "hit_yield_total": 0.6449483067134999,
  "pollution_rate_total": 0.7539018490290941,
  "avg_update_time_s": 0.2712113476440007,
  "update_time_total_s": 24.40902128796006
}