{
  "dataset": "wiki2018",
  "model": "ilnse_A2_fixed",
  "feature_set": "A2",
  "cache_size_objects": 16123,
  "total_requests": 10000000,
  "warmup_requests": 1000000,
  "slot_size": 100000,
  "slot_log_path": "results/wiki2018/001_ilnse_A2_fixed_16123.jsonl",
  "hit_ratio": 0.4632322222222222,
  "cache_hits": 4169090,
  "cache_requests": 9000000,
  "num_slots": 100,
  "warmup_slots": 10,
  "cache_slots": 90,
  "pop_top_percent": 0.2,
  "label_topk_rounding": "floor",
  "label_tie_break": "none",
  "admission_policy": "top_capacity_rate",
  "admission_capacity_alpha": 0.08,
  "enable_drift": false,
  "enable_guardrails": false,
  "fixed_budget_alpha": 0.08,
  "drift_alpha_min": 0.005,
  "drift_alpha_max": 0.2,
  "drift_sensitivity": 1.0,
  "drift_ema_alpha": 0.3,
  "drift_weight_jsd": 0.4,
  "drift_weight_overlap": 0.6,
  "drift_gain": 1.0,
  "drift_alpha_floor_mult": 0.7,
  "admission_precision_target": 0.12,
  "admission_precision_sensitivity": 1.0,
  "capacity_alpha_scale_min": 0.4,
  "feature_windows": {
    "short": 1,
    "mid": 7,
    "long": 30
  },
  "pollution_window_slots": 1,
  "hit_contribution": {
    "hits_from_admitted": 95541,
    "reject_requests_total": 4419077
  },
  "num_features": 10,
  "slots_processed": 100,
  "cache_slots_processed": 90,
  "update_slots": 100,
  "miss_requests_total": 4830910,
  "miss_candidates_total": 4535177,
  "score_eval_slots": 90,
  "score_eval_n_avg": 50390.85555555556,
  "score_eval_pos_avg": 6614.544444444445,
  "score_auc_avg": 0.6346963398709391,
  "score_ap_avg": 0.21455163258965435,
  "score_precK_avg": 0.2434167267808284,
  "score_acc_avg": 0.8697951607862895,
  "score_precK_hr_next_corr": -0.4354503048186047,
  "score_precK_hr_next_n": 89,
  "score_gate_k_avg": 2520.0555555555557,
  "score_gate_applied_slots": 0,
  "fill_phase_slots": 0,
  "fill_min_budget_avg": null,
  "pressure_mult_avg": 1.0,
  "score_spread_avg": 0.07224633150789866,
  "quality_mult_avg": 0.9117630425033637,
  "quality_good_slots": 20,
  "quality_bad_slots": 70,
  "quality_good_ratio": 0.2222222222222222,
  "admission_precision_eff_avg": 0.20065325320094057,
  "score_auc_count": 90,
  "score_ap_count": 90,
  "score_precK_count": 90,
  "score_acc_count": 90,
  "admit_budget_total": 116100,
  "admit_requests_total": 116100,
  "reject_requests_total": 4419077,
  "admit_selected_total": 116100,
  "admit_applied_total": 114810,
  "admit_true_popular_total": 17534,
  "hits_from_admitted_total": 95541,
  "pollution_total": 114810,
  "pollution_count": 45834,
  "admission_precision_total": 0.15272188833725286,
  "hit_yield_total": 0.8321661876143193,
  "pollution_rate_total": 0.39921609615887116,
  "miss_rate_avg": 0.5367677777777776,
  "jsd_freq_avg": 0.3245708176169089,
  "topk_overlap_w_avg": 0.3697079753926526,
  "drift_raw_avg": 0.5080035418111721,
  "drift_norm_avg": 0.5384462982956403,
  "admission_alpha_avg": 0.08000000000000006,
  "admission_alpha_min": 0.08,
  "admission_alpha_max": 0.08,
  "avg_update_time_s": 0.7958813264290803,
  "avg_score_time_s": 0.37103465221104365,
  "score_time_total_s": 33.39311869899393,
  "cache_inserts_total": 114810,
  "cache_evictions_total": 98687,
  "cache_inserts_avg": 1275.6666666666667,
  "cache_evictions_avg": 1096.5222222222221,
  "update_time_total_s": 79.58813264290802
}