{
  "dataset": "wiki2018",
  "model": "ilnse_A2_guard_only",
  "feature_set": "A2",
  "cache_size_objects": 20154,
  "total_requests": 10000000,
  "warmup_requests": 1000000,
  "slot_size": 100000,
  "slot_log_path": "results/wiki2018/003_ilnse_A2_guard_only_20154.jsonl",
  "hit_ratio": 0.48253922222222223,
  "cache_hits": 4342853,
  "cache_requests": 9000000,
  "num_slots": 100,
  "warmup_slots": 10,
  "cache_slots": 90,
  "pop_top_percent": 0.2,
  "label_topk_rounding": "floor",
  "label_tie_break": "none",
  "admission_policy": "top_capacity_rate",
  "admission_capacity_alpha": 0.08,
  "enable_drift": false,
  "enable_guardrails": true,
  "fixed_budget_alpha": null,
  "drift_alpha_min": 0.005,
  "drift_alpha_max": 0.2,
  "drift_sensitivity": 1.0,
  "drift_ema_alpha": 0.3,
  "drift_weight_jsd": 0.4,
  "drift_weight_overlap": 0.6,
  "drift_gain": 1.0,
  "drift_alpha_floor_mult": 0.7,
  "admission_precision_target": 0.12,
  "admission_precision_sensitivity": 1.0,
  "capacity_alpha_scale_min": 0.4,
  "feature_windows": {
    "short": 1,
    "mid": 7,
    "long": 30
  },
  "pollution_window_slots": 1,
  "hit_contribution": {
    "hits_from_admitted": 79544,
    "reject_requests_total": 4302826
  },
  "num_features": 10,
  "guard_mode": "conditional_gate",
  "slots_processed": 100,
  "cache_slots_processed": 90,
  "update_slots": 100,
  "miss_requests_total": 4657147,
  "miss_candidates_total": 4403782,
  "score_eval_slots": 90,
  "score_eval_n_avg": 48930.91111111111,
  "score_eval_pos_avg": 6146.488888888889,
  "score_auc_avg": 0.6229050662515315,
  "score_ap_avg": 0.19227973202449775,
  "score_precK_avg": 0.21979980797195406,
  "score_acc_avg": 0.875697465787631,
  "score_precK_hr_next_corr": -0.24152626816964662,
  "score_precK_hr_next_n": 89,
  "score_gate_k_avg": 2447.0666666666666,
  "score_gate_percent_avg": 0.04999999999999991,
  "score_gate_applied_slots": 1,
  "fill_phase_slots": 5,
  "fill_min_budget_avg": 1008.0,
  "pressure_mult_avg": 1.2925824616454764,
  "score_spread_avg": 0.05813519529074341,
  "quality_mult_avg": 0.9142786625515436,
  "quality_good_slots": 23,
  "quality_bad_slots": 67,
  "quality_good_ratio": 0.25555555555555554,
  "admission_precision_eff_avg": 0.15665283440137617,
  "score_auc_count": 90,
  "score_ap_count": 90,
  "score_precK_count": 90,
  "score_acc_count": 90,
  "admit_budget_total": 100956,
  "admit_requests_total": 100956,
  "reject_requests_total": 4302826,
  "admit_selected_total": 100956,
  "admit_applied_total": 99870,
  "admit_true_popular_total": 12825,
  "hits_from_admitted_total": 79544,
  "pollution_total": 99870,
  "pollution_count": 46373,
  "admission_precision_total": 0.12841694202463202,
  "hit_yield_total": 0.7964754180434565,
  "pollution_rate_total": 0.464333633723841,
  "miss_rate_avg": 0.5174607777777775,
  "jsd_freq_avg": 0.324570817616909,
  "topk_overlap_w_avg": 0.3697079753926525,
  "drift_raw_avg": 0.5080035418111722,
  "drift_norm_avg": 0.5384462982956383,
  "admission_alpha_avg": 0.04251868063599424,
  "admission_alpha_min": 0.032,
  "admission_alpha_max": 0.2,
  "avg_update_time_s": 0.5941067294293316,
  "avg_score_time_s": 0.26087476381184793,
  "score_time_total_s": 23.478728743066313,
  "cache_inserts_total": 99870,
  "cache_evictions_total": 79716,
  "cache_inserts_avg": 1109.6666666666667,
  "cache_evictions_avg": 885.7333333333333,
  "update_time_total_s": 59.41067294293316
}