{
  "dataset": "wikipedia_september_2007",
  "model": "ilnse_A2_guard_full_nb_drift_piecewise_aggressive",
  "feature_set": "A2",
  "base_learner": "nb",
  "drift_control_mode": "piecewise",
  "drift_norm_power": 0.7,
  "drift_threshold": 0.5,
  "drift_alpha_low": 0.02,
  "drift_alpha_high": 0.3,
  "drift_use_capacity_scale": true,
  "cache_size_objects": 45831,
  "total_requests": 9000000,
  "warmup_requests": 1000000,
  "slot_size": 100000,
  "slot_log_path": "results/wikipedia_september_2007/001_ilnse_A2_guard_full_nb_drift_piecewise_aggressive_45831.jsonl",
  "hit_ratio": 0.689805375,
  "cache_hits": 5518443,
  "cache_requests": 8000000,
  "num_slots": 90,
  "warmup_slots": 10,
  "cache_slots": 80,
  "pop_top_percent": 0.2,
  "label_topk_rounding": "floor",
  "label_tie_break": "none",
  "admission_policy": "top_capacity_rate",
  "admission_capacity_alpha": 0.08,
  "drift_alpha_min": 0.005,
  "drift_alpha_max": 0.4,
  "drift_sensitivity": 1.0,
  "drift_ema_alpha": 0.3,
  "drift_weight_jsd": 0.4,
  "drift_weight_overlap": 0.6,
  "drift_gain": 0.0,
  "drift_alpha_floor_mult": 0.7,
  "admission_precision_target": 0.12,
  "admission_precision_sensitivity": 1.0,
  "capacity_alpha_scale_min": 0.4,
  "feature_windows": {
    "short": 1,
    "mid": 7,
    "long": 30
  },
  "pollution_window_slots": 1,
  "hit_contribution": {
    "hits_from_admitted": 84246,
    "reject_requests_total": 2210329
  },
  "num_features": 10,
  "slots_processed": 90,
  "cache_slots_processed": 80,
  "update_slots": 90,
  "miss_requests_total": 2481557,
  "miss_candidates_total": 2367206,
  "score_eval_slots": 80,
  "score_eval_n_avg": 29590.075,
  "score_eval_pos_avg": 3648.825,
  "score_auc_avg": 0.5697553648064598,
  "score_ap_avg": 0.15436177683089794,
  "score_precK_avg": 0.1887407605335692,
  "score_acc_avg": 0.877616078776706,
  "score_precK_hr_next_corr": -0.8087545141521786,
  "score_precK_hr_next_n": 79,
  "score_gate_k_avg": 1479.9875,
  "score_gate_applied_slots": 69,
  "fill_phase_slots": 3,
  "fill_min_budget_avg": 2292.0,
  "pressure_mult_avg": 0.8432963505431792,
  "score_spread_avg": 0.030030238004434724,
  "quality_mult_avg": 0.7290327047821334,
  "admission_precision_eff_avg": 0.03592350809833949,
  "score_auc_count": 80,
  "score_ap_count": 80,
  "score_precK_count": 80,
  "score_acc_count": 80,
  "admit_budget_total": 156877,
  "admit_requests_total": 156877,
  "reject_requests_total": 2210329,
  "admit_selected_total": 156877,
  "admit_applied_total": 156033,
  "admit_true_popular_total": 7026,
  "hits_from_admitted_total": 84246,
  "pollution_total": 156033,
  "pollution_count": 116474,
  "admission_precision_total": 0.04502893618657592,
  "hit_yield_total": 0.5399242467939475,
  "pollution_rate_total": 0.7464702979497927,
  "miss_rate_avg": 0.310194625,
  "jsd_freq_avg": 0.1330111973939073,
  "topk_overlap_w_avg": 0.6759815553111451,
  "drift_raw_avg": 0.24761554577087583,
  "drift_norm_avg": 0.5714646362577593,
  "admission_alpha_avg": 0.27473401134600495,
  "admission_alpha_min": 0.02,
  "admission_alpha_max": 0.3766243211792087,
  "avg_update_time_s": 0.45346439141236866,
  "update_time_total_s": 40.81179522711318
}