{
  "dataset": "wiki2018",
  "model": "ilnse_A2_guard_no_guard_nb_overhead",
  "feature_set": "A2",
  "base_learner": "nb",
  "cache_size_objects": 16123,
  "total_requests": 10000000,
  "warmup_requests": 1000000,
  "slot_size": 100000,
  "slot_log_path": "results/overhead/wiki2018/001_ilnse_A2_guard_no_guard_nb_overhead_16123.jsonl",
  "hit_ratio": 0.4594252222222222,
  "cache_hits": 4134827,
  "cache_requests": 9000000,
  "num_slots": 100,
  "warmup_slots": 10,
  "cache_slots": 90,
  "pop_top_percent": 0.2,
  "label_topk_rounding": "floor",
  "label_tie_break": "none",
  "admission_policy": "top_capacity_rate",
  "admission_capacity_alpha": 0.08,
  "drift_alpha_min": 0.005,
  "drift_alpha_max": 0.2,
  "drift_sensitivity": 1.0,
  "drift_ema_alpha": 0.3,
  "drift_weight_jsd": 0.4,
  "drift_weight_overlap": 0.6,
  "drift_gain": 0.0,
  "drift_alpha_floor_mult": 0.7,
  "admission_precision_target": 0.12,
  "admission_precision_sensitivity": 0.0,
  "capacity_alpha_scale_min": 0.4,
  "feature_windows": {
    "short": 1,
    "mid": 7,
    "long": 30
  },
  "pollution_window_slots": 1,
  "hit_contribution": {
    "hits_from_admitted": 70166,
    "reject_requests_total": 4494199
  },
  "num_features": 10,
  "slots_processed": 100,
  "cache_slots_processed": 90,
  "update_slots": 100,
  "miss_requests_total": 4865173,
  "miss_candidates_total": 4555605,
  "score_eval_slots": 90,
  "score_eval_n_avg": 50617.833333333336,
  "score_eval_pos_avg": 6696.666666666667,
  "score_auc_avg": 0.6355547839754951,
  "score_ap_avg": 0.21544633543067807,
  "score_precK_avg": 0.24463363868703852,
  "score_acc_avg": 0.8691158339408371,
  "score_precK_hr_next_corr": -0.5782311112826233,
  "score_precK_hr_next_n": 89,
  "score_gate_k_avg": 50617.833333333336,
  "score_gate_applied_slots": 0,
  "fill_phase_slots": 18,
  "fill_min_budget_avg": 807.0,
  "pressure_mult_avg": 1.2702873888888886,
  "score_spread_avg": 0.07436246812544753,
  "quality_mult_avg": 1.0,
  "admission_precision_eff_avg": 0.22201895348332049,
  "score_auc_count": 90,
  "score_ap_count": 90,
  "score_precK_count": 90,
  "score_acc_count": 90,
  "admit_budget_total": 61406,
  "admit_requests_total": 61406,
  "reject_requests_total": 4494199,
  "admit_selected_total": 61406,
  "admit_applied_total": 60764,
  "admit_true_popular_total": 10617,
  "hits_from_admitted_total": 70166,
  "pollution_total": 60764,
  "pollution_count": 22987,
  "admission_precision_total": 0.17472516621683892,
  "hit_yield_total": 1.1547297742084128,
  "pollution_rate_total": 0.3782996511092094,
  "miss_rate_avg": 0.5405747777777777,
  "jsd_freq_avg": 0.3245708176169089,
  "topk_overlap_w_avg": 0.3697079753926526,
  "drift_raw_avg": 0.5080035418111719,
  "drift_norm_avg": 0.5384462982956405,
  "admission_alpha_avg": 0.03200000000000002,
  "admission_alpha_min": 0.032,
  "admission_alpha_max": 0.032,
  "avg_update_time_s": 1.236794719141908,
  "avg_feat_time_s": 2.737051404690137,
  "avg_score_time_s": 0.7988074246363248,
  "avg_guard_time_s": 0.23862794792628847,
  "avg_select_time_s": 0.01876109918463044,
  "avg_slot_time_s": 5.030042595579289,
  "update_time_total_s": 123.6794719141908,
  "feat_time_total_s": 273.7051404690137,
  "score_time_total_s": 79.88074246363249,
  "guard_time_total_s": 23.862794792628847,
  "select_time_total_s": 1.8761099184630439,
  "slot_time_total_s": 503.0042595579289,
  "max_feature_bytes": 8000000,
  "rss_max_kb": 3984650240.0,
  "rss_max_mb": 3891260.0
}