{
  "dataset": "wiki2018",
  "model": "ilnse_A2",
  "feature_set": "A2",
  "cache_size_objects": 60463,
  "total_requests": 10000000,
  "warmup_requests": 1000000,
  "slot_size": 100000,
  "slot_log_path": "results/wiki2018/008_ilnse_A2_60463.jsonl",
  "hit_ratio": 0.5590672222222223,
  "cache_hits": 5031605,
  "cache_requests": 9000000,
  "num_slots": 100,
  "warmup_slots": 10,
  "cache_slots": 90,
  "pop_top_percent": 0.2,
  "label_topk_rounding": "floor",
  "label_tie_break": "none",
  "admission_policy": "top_capacity_rate",
  "admission_capacity_alpha": 0.08,
  "drift_alpha_min": 0.02,
  "drift_alpha_max": 0.2,
  "drift_weight_miss": 0.5,
  "drift_weight_jsd": 0.5,
  "drift_sensitivity": 1.0,
  "admission_precision_target": 0.12,
  "admission_precision_sensitivity": 1.0,
  "feature_windows": {
    "short": 1,
    "mid": 7,
    "long": 30
  },
  "pollution_window_slots": 1,
  "hit_contribution": {
    "hits_from_admitted": 71289,
    "reject_requests_total": 3654941
  },
  "num_features": 10,
  "slots_processed": 100,
  "cache_slots_processed": 90,
  "update_slots": 100,
  "miss_requests_total": 3968395,
  "miss_candidates_total": 3816297,
  "admit_budget_total": 161356,
  "admit_requests_total": 161356,
  "reject_requests_total": 3654941,
  "admit_selected_total": 161356,
  "admit_applied_total": 159405,
  "admit_true_popular_total": 10056,
  "hits_from_admitted_total": 71289,
  "pollution_total": 159405,
  "pollution_count": 108242,
  "admission_precision_total": 0.06308459584078291,
  "hit_yield_total": 0.44721934694645715,
  "pollution_rate_total": 0.6790376713402967,
  "miss_rate_avg": 0.4409327777777779,
  "jsd_freq_avg": 0.0009233909061876254,
  "drift_score_avg": 0.22092808434198272,
  "admission_alpha_avg": 0.02964152480392416,
  "admission_alpha_min": 0.02,
  "admission_alpha_max": 0.2,
  "avg_update_time_s": 0.6356711516001087,
  "update_time_total_s": 63.56711516001087
}